github_releaser/__init__.py
github_releaser/exceptions.py
github_releaser/github_releaser.py
github_releaser/release.py
github_releaser/cmd/__init__.py
github_releaser/cmd/asset.py
github_releaser/cmd/push.py
github_releaser/cmd/release.py
github_releaser-0.2.1.dist-info/AUTHORS.md
github_releaser-0.2.1.dist-info/LICENSE
github_releaser-0.2.1.dist-info/METADATA
github_releaser-0.2.1.dist-info/WHEEL
github_releaser-0.2.1.dist-info/entry_points.txt
github_releaser-0.2.1.dist-info/top_level.txt
github_releaser-0.2.1.dist-info/RECORD
