Metadata-Version: 2.1
Name: github-releaser
Version: 0.2.1
Summary: CLI for creating releases on GitHub.
Home-page: https://github.com/dfurtado/github-releaser
Author: Daniel Furtado
Author-email: daniel@dfurtado.com
License: MIT license
Keywords: github-releaser
Platform: UNKNOWN
Classifier: Development Status :: 2 - Pre-Alpha
Classifier: Intended Audience :: Developers
Classifier: License :: OSI Approved :: MIT License
Classifier: Natural Language :: English
Classifier: Programming Language :: Python :: 3
Classifier: Programming Language :: Python :: 3.5
Classifier: Programming Language :: Python :: 3.6
Classifier: Programming Language :: Python :: 3.7
Classifier: Programming Language :: Python :: 3.8
Requires-Python: >=3.5
Requires-Dist: Click (>=7.0)
Requires-Dist: yaspin (>=0.17.0)
Requires-Dist: requests (>=2.0.1)
